uiScrypt/__init__.py
uiScrypt/uiScrypt.py
uiScrypt/ui_Scrypt.py
uiScrypt/version.py
uiScrypt-2.0.1.dist-info/LICENSE
uiScrypt-2.0.1.dist-info/METADATA
uiScrypt-2.0.1.dist-info/WHEEL
uiScrypt-2.0.1.dist-info/entry_points.txt
uiScrypt-2.0.1.dist-info/top_level.txt
uiScrypt-2.0.1.dist-info/RECORD
