Metadata-Version: 2.1
Name: uiScrypt
Version: 2.0.1
Summary: A simple GUI app for generating Scrypt keys
Home-page: https://github.com/NotStatilko/uiScrypt
Download-URL: https://github.com/NotStatilko/uiScrypt/archive/refs/tags/v2.0.1.tar.gz
Author-email: thenonproton@pm.me
License: MIT
License-File: LICENSE
Requires-Dist: pillow ==9.5.0
Requires-Dist: pyqt5 ==5.15.9
Requires-Dist: qrcode ==6.1
